n8n_sdk_python/__init__.py
n8n_sdk_python/client/__init__.py
n8n_sdk_python/client/audit.py
n8n_sdk_python/client/base.py
n8n_sdk_python/client/connections.py
n8n_sdk_python/client/credentials.py
n8n_sdk_python/client/executions.py
n8n_sdk_python/client/nodes.py
n8n_sdk_python/client/projects.py
n8n_sdk_python/client/source_control.py
n8n_sdk_python/client/tags.py
n8n_sdk_python/client/users.py
n8n_sdk_python/client/variables.py
n8n_sdk_python/client/workflows.py
n8n_sdk_python/models/__init__.py
n8n_sdk_python/models/audit.py
n8n_sdk_python/models/base.py
n8n_sdk_python/models/credentials.py
n8n_sdk_python/models/executions.py
n8n_sdk_python/models/nodes.py
n8n_sdk_python/models/projects.py
n8n_sdk_python/models/source_control.py
n8n_sdk_python/models/users.py
n8n_sdk_python/models/variables.py
n8n_sdk_python/models/workflows.py
n8n_sdk_python/utils/__init__.py
n8n_sdk_python/utils/errors.py
n8n_sdk_python/utils/logger.py
n8n_sdk_python-0.1.3.dist-info/licenses/LICENSE
n8n_sdk_python-0.1.3.dist-info/METADATA
n8n_sdk_python-0.1.3.dist-info/WHEEL
n8n_sdk_python-0.1.3.dist-info/top_level.txt
n8n_sdk_python-0.1.3.dist-info/RECORD
