Metadata-Version: 2.4
Name: n8n-sdk-python
Version: 0.1.3
Summary: A Python SDK for the n8n automation platform.
Author-email: Eric LEE <ericlee050828@gmail.com>
License-Expression: MIT
Project-URL: Homepage, https://github.com/eric050828/n8n-sdk-python
Project-URL: Repository, https://github.com/eric050828/n8n-sdk-python
Project-URL: Bug Tracker, https://github.com/eric050828/n8n-sdk-python/issues
Project-URL: Documentation, https://github.com/eric050828/n8n-sdk-python#readme
Keywords: n8n,sdk,python,automation,api-client,n8n-client,workflow
Classifier: Development Status :: 3 - Alpha
Classifier: Programming Language :: Python :: 3
Classifier: Programming Language :: Python :: 3.8
Classifier: Programming Language :: Python :: 3.9
Classifier: Programming Language :: Python :: 3.10
Classifier: Programming Language :: Python :: 3.11
Classifier: Programming Language :: Python :: 3.12
Classifier: Programming Language :: Python :: 3.13
Classifier: Operating System :: OS Independent
Classifier: Intended Audience :: Developers
Classifier: Topic :: Software Development :: Libraries :: Python Modules
Classifier: Topic :: Internet
Classifier: Framework :: AsyncIO
Classifier: Typing :: Typed
Requires-Python: >=3.8
License-File: LICENSE
Requires-Dist: httpx>=0.28.0
Requires-Dist: pydantic>=2.10.0
Requires-Dist: python-dotenv>=1.0.0
Provides-Extra: dev
Requires-Dist: pytest<9.0,>=6.0; extra == "dev"
Requires-Dist: pytest-asyncio<0.24,>=0.15; extra == "dev"
Requires-Dist: pre-commit<4.0,>=2.0; extra == "dev"
Requires-Dist: ruff; extra == "dev"
Requires-Dist: mypy; extra == "dev"
Dynamic: license-file
